simple_nn_cooper/__init__.py
simple_nn_cooper/nn/__init__.py
simple_nn_cooper/nn/core.py
simple_nn_cooper/utils/__init__.py
simple_nn_cooper/utils/utilities.py
simple_nn_cooper-0.0.1.dist-info/LICENSE
simple_nn_cooper-0.0.1.dist-info/METADATA
simple_nn_cooper-0.0.1.dist-info/WHEEL
simple_nn_cooper-0.0.1.dist-info/top_level.txt
simple_nn_cooper-0.0.1.dist-info/RECORD
