Metadata-Version: 2.1
Name: simple-nn-cooper
Version: 0.0.1
Summary: This is a mini deep learning framework
Home-page: UNKNOWN
Author: cooper
Author-email: 497464497@qq.com
License: UNKNOWN
Platform: UNKNOWN
Classifier: Programming Language :: Python :: 3
Classifier: License :: OSI Approved :: MIT License
Classifier: Operating System :: OS Independent
Requires-Python: >=3.6
